camel/__init__.py
camel/agent.py
camel/api.py
camel/exceptions.py
camel/models.py
camel/streaming.py
camel/tools.py
camel/utils.py
camel_py-0.2.0.dist-info/METADATA
camel_py-0.2.0.dist-info/WHEEL
camel_py-0.2.0.dist-info/RECORD
