Metadata-Version: 2.4
Name: camel-py
Version: 0.2.0
Summary: A lightweight Python client for Ollama with context management and streaming support.
Project-URL: Homepage, https://github.com/Narendrakumar-Suresh/camel
Project-URL: Repository, https://github.com/Narendrakumar-Suresh/camel
Project-URL: Issues, https://github.com/Narendrakumar-Suresh/camel/issues
Author-email: Narendrakumar S <narendrkumarsuresh@gmail.com>
License: MIT
Requires-Python: >=3.12
Requires-Dist: httpx>=0.28.1
Requires-Dist: ruff>=0.14.10
Requires-Dist: yaspin>=3.1.0
